panopto/__init__.py
panopto/auth.py
panopto/session.py
panopto/upload.py
panopto/__pycache__/__init__.cpython-313.pyc
panopto/__pycache__/auth.cpython-313.pyc
panopto/__pycache__/upload.cpython-313.pyc
panopto/tests/__init__.py
panopto/tests/patches.py
panopto/tests/test_auth.py
panopto/tests/test_upload.py
panopto/tests/__pycache__/__init__.cpython-313.pyc
panopto/tests/__pycache__/patches.cpython-313.pyc
panopto/tests/__pycache__/test_auth.cpython-313-pytest-8.3.4.pyc
panopto/tests/__pycache__/test_upload.cpython-313-pytest-8.3.4.pyc
pypanopto-0.3.0.dist-info/LICENSE
pypanopto-0.3.0.dist-info/METADATA
pypanopto-0.3.0.dist-info/WHEEL
pypanopto-0.3.0.dist-info/top_level.txt
pypanopto-0.3.0.dist-info/RECORD
